CHANGELOG.rst
ant_connect/__init__.py
ant_connect/api_connector.py
ant_connect/config.py
ant_connect/document.py
ant_connect/enums.py
ant_connect/models.py
ant_connect/query_builder.py
ant_connect/utils/__init__.py
ant_connect/utils/decorators.py
ant_connect/utils/manual_functions.py
ant_connect/utils/model_base_class.py
ant_connect/utils/query_operators.py
ant_connect/utils/response.py
ant_connect/v1/__init__.py
ant_connect/v1/api.py
ant_connect_py-2.0.8.dist-info/AUTHORS.rst
ant_connect_py-2.0.8.dist-info/LICENSE
ant_connect_py-2.0.8.dist-info/METADATA
ant_connect_py-2.0.8.dist-info/WHEEL
ant_connect_py-2.0.8.dist-info/entry_points.txt
ant_connect_py-2.0.8.dist-info/RECORD
