Metadata-Version: 2.1
Name: ant_connect_py
Version: 2.0.8
Summary: Release of the new V2 python package.
Home-page: https://antcde.io/
License: Proprietary - ANTCDE
Author: LEED
Author-email: dervis.van.leersum@antcde.io
Requires-Python: >=3.8,<3.13
Classifier: License :: Other/Proprietary License
Classifier: Programming Language :: Python
Classifier: Programming Language :: Python :: 3
Classifier: Programming Language :: Python :: 3.8
Classifier: Programming Language :: Python :: 3.9
Classifier: Programming Language :: Python :: 3.10
Classifier: Programming Language :: Python :: 3.11
Classifier: Programming Language :: Python :: 3.12
Classifier: Topic :: Software Development :: Libraries :: Python Modules
Requires-Dist: pydantic (>=2.5.2,<3.0.0)
Requires-Dist: requests (>=2.31.0,<3.0.0)
Project-URL: Documentation, https://docs.antcde.io/
